wide_and_deep/__init__.py
wide_and_deep/_nbdev.py
wide_and_deep/model.py
wide_and_deep/prediction.py
wide_and_deep-1.0.0.dist-info/LICENSE.md
wide_and_deep-1.0.0.dist-info/METADATA
wide_and_deep-1.0.0.dist-info/WHEEL
wide_and_deep-1.0.0.dist-info/entry_points.txt
wide_and_deep-1.0.0.dist-info/top_level.txt
wide_and_deep-1.0.0.dist-info/RECORD
