Metadata-Version: 2.1
Name: wide-and-deep
Version: 1.0.0
Summary: Use wide and deep model to do multi-classification tasks.
Home-page: https://github.com/JiaxiangBU/wide_and_deep
Author: Jiaxiang Li
Author-email: alex.lijiaxiang@foxmail.com
License: Apache Software License 2.0
Keywords: deep-learning
Platform: UNKNOWN
Classifier: Development Status :: 3 - Alpha
Classifier: Intended Audience :: Developers
Classifier: License :: OSI Approved :: Apache Software License
Classifier: Natural Language :: English
Classifier: Programming Language :: Python :: 3.6
Classifier: Programming Language :: Python :: 3.7
Classifier: Programming Language :: Python :: 3.8
Requires-Python: >=3.6
